e_commerce_franck_sdk/__init__.py
e_commerce_franck_sdk/e_commerce_client.py
e_commerce_franck_sdk/e_commerce_config.py
e_commerce_franck_sdk/schemas/__init__.py
e_commerce_franck_sdk/schemas/schemas.py
e_commerce_franck_sdk-0.0.2.dist-info/METADATA
e_commerce_franck_sdk-0.0.2.dist-info/WHEEL
e_commerce_franck_sdk-0.0.2.dist-info/top_level.txt
e_commerce_franck_sdk-0.0.2.dist-info/RECORD
