Metadata-Version: 2.4
Name: e_commerce_franck_sdk
Version: 0.0.2
Summary: Software Development Kit (SDK) pour accéder à l'API E-Commerce (Data Analysts/ Data Scientists)
Author: Franck BATTY
Classifier: Development Status :: 3 - Alpha
Classifier: Programming Language :: Python :: 3
Classifier: License :: OSI Approved :: MIT License
Classifier: Operating System :: OS Independent
Requires-Python: >=3.10
Requires-Dist: httpx>=0.28.1
Requires-Dist: pydantic>=2.11.7
Requires-Dist: backoff>=2.2.1
Requires-Dist: pandas>=2.2.3
Requires-Dist: python-dotenv
